{
    "behavior": "", 
    "checkable": false, 
    "class": "div", 
    "clickable": false, 
    "content-desc": "", 
    "enabled": false, 
    "focusable": false, 
    "focused": false, 
    "hash": "CP14quA/mgFMKlUdLWScLw==\n", 
    "height": 178, 
    "hier_level": 0, 
    "human_hash": "div_X3022_Y830_W200_H178", 
    "index": -1, 
    "internal": {
        "elem_dict": {
            "attributes": {
                "data-radium": "true"
            }, 
            "background-color": "rgba(0, 0, 0, 0)", 
            "class": "div", 
            "color": "rgb(17, 17, 17)", 
            "domLevel": 9, 
            "flags": {
                "checkable": false, 
                "clickable": false, 
                "enabled": false, 
                "focusable": false, 
                "focused": false, 
                "scrollable": false
            }, 
            "font-family": "\"Helvetica Neue\", Helvetica, Arial, sans-serif", 
            "font-weight": "500", 
            "fontSize": 12, 
            "height": 89, 
            "identifier": "", 
            "is-focused": false, 
            "is-hidden": false, 
            "name": "", 
            "tagName": "div", 
            "text": "Midnight Navy", 
            "type": "", 
            "value": "", 
            "width": 100, 
            "x": 1511, 
            "xPercent": 78.6767578125, 
            "y": 415, 
            "yPercent": 46.05555555555556
        }, 
        "location": {
            "x": 1511, 
            "y": 415
        }, 
        "size": {
            "height": 89, 
            "width": 100
        }, 
        "tag_name": "div", 
        "text": "Midnight Navy"
    }, 
    "is_transformed": true, 
    "package": "", 
    "password": false, 
    "resource-id": "", 
    "scrollable": false, 
    "tag_name": "div", 
    "text": "Midnight Navy", 
    "transformed": true, 
    "width": 200, 
    "x": 3022, 
    "y": 830
}