{
    "behavior": "", 
    "checkable": false, 
    "class": "div", 
    "clickable": false, 
    "content-desc": "", 
    "enabled": false, 
    "focusable": false, 
    "focused": false, 
    "hash": "zkUligJ92uxkELb+a8tOiQ==\n", 
    "height": 56, 
    "hier_level": 0, 
    "human_hash": "div_X1468_Y370_W116_H56", 
    "index": -1, 
    "internal": {
        "elem_dict": {
            "attributes": {
                "class": "css-123i213 e4f9riy2"
            }, 
            "background-color": "rgb(255, 255, 255)", 
            "class": "div", 
            "color": "rgb(17, 17, 17)", 
            "cssClass": "css-123i213 e4f9riy2", 
            "domLevel": 16, 
            "flags": {
                "checkable": false, 
                "clickable": false, 
                "enabled": false, 
                "focusable": false, 
                "focused": false, 
                "scrollable": false
            }, 
            "font-family": "\"Helvetica Neue\", Helvetica, Arial, sans-serif", 
            "font-weight": "400", 
            "fontSize": 16, 
            "height": 28, 
            "identifier": "", 
            "is-focused": false, 
            "is-hidden": false, 
            "name": "", 
            "tagName": "div", 
            "text": "12345678910", 
            "type": "", 
            "value": "", 
            "width": 58, 
            "x": 734, 
            "xPercent": 38.51377952755905, 
            "y": 185, 
            "yPercent": 10.059815116911365
        }, 
        "location": {
            "x": 734, 
            "y": 185
        }, 
        "size": {
            "height": 28, 
            "width": 58
        }, 
        "tag_name": "div", 
        "text": "12345678910"
    }, 
    "is_transformed": true, 
    "package": "", 
    "password": false, 
    "resource-id": "", 
    "scrollable": false, 
    "tag_name": "div", 
    "text": "12345678910", 
    "transformed": true, 
    "width": 116, 
    "x": 1468, 
    "y": 370
}