{
    "behavior": "", 
    "checkable": false, 
    "class": "span", 
    "clickable": false, 
    "content-desc": "", 
    "enabled": false, 
    "focusable": false, 
    "focused": false, 
    "hash": "6k/UASswbu0tzOZ6Wpz2lg==\n", 
    "height": 40, 
    "hier_level": 0, 
    "human_hash": "span_X374_Y956_W64_H40", 
    "index": -1, 
    "internal": {
        "elem_dict": {
            "attributes": {
                "class": "filter-item__item-label"
            }, 
            "background-color": "rgba(0, 0, 0, 0)", 
            "class": "span", 
            "color": "rgb(0, 0, 0)", 
            "cssClass": "filter-item__item-label", 
            "domLevel": 23, 
            "flags": {
                "checkable": false, 
                "clickable": false, 
                "enabled": false, 
                "focusable": false, 
                "focused": false, 
                "scrollable": false
            }, 
            "font-family": "\"Helvetica Neue\", Helvetica, Arial, sans-serif", 
            "font-weight": "400", 
            "fontSize": 12, 
            "height": 20, 
            "identifier": "", 
            "is-focused": false, 
            "is-hidden": false, 
            "name": "", 
            "tagName": "span", 
            "text": "Green", 
            "type": "", 
            "value": "", 
            "width": 32, 
            "x": 187, 
            "xPercent": 9.793307086614174, 
            "y": 478, 
            "yPercent": 35.83208395802099
        }, 
        "location": {
            "x": 187, 
            "y": 478
        }, 
        "size": {
            "height": 20, 
            "width": 32
        }, 
        "tag_name": "span", 
        "text": "Green"
    }, 
    "is_transformed": true, 
    "package": "", 
    "password": false, 
    "resource-id": "", 
    "scrollable": false, 
    "tag_name": "span", 
    "text": "Green", 
    "transformed": true, 
    "width": 64, 
    "x": 374, 
    "y": 956
}